matrix/__init__.py
matrix/chatbot.py
matrix/cli.py
matrix/maze.py
matrix/password.py
matrix/wordfreq.py
matrix_tasks-1.0.0.dist-info/METADATA
matrix_tasks-1.0.0.dist-info/WHEEL
matrix_tasks-1.0.0.dist-info/entry_points.txt
matrix_tasks-1.0.0.dist-info/top_level.txt
matrix_tasks-1.0.0.dist-info/RECORD
