Metadata-Version: 2.4
Name: matrix-tasks
Version: 1.0.0
Summary: Matrix Internship Tasks: word frequency, password checker, maze solver, chatbot with memory
Author-email: Dipaon <dipaon11@gmail.com>
Requires-Python: >=3.10
